MANIFEST.in
README.rst
setup.py
ToDo/__init__.py
ToDo/settings.py
ToDo/urls.py
ToDo/wsgi.py
lists/__init__.py
lists/admin.py
lists/forms.py
lists/models.py
lists/urls.py
lists/views.py
lists/migrations/0001_initial.py
lists/migrations/0002_group_task.py
lists/migrations/__init__.py
lists/test_cases/__init__.py
lists/test_cases/tests.py
test_todo.egg-info/PKG-INFO
test_todo.egg-info/SOURCES.txt
test_todo.egg-info/dependency_links.txt
test_todo.egg-info/requires.txt
test_todo.egg-info/top_level.txt